Viajes/Clases_viajes.py
Viajes/__init__.py
LibreriaViajes_UxueAinara-0.5.6.dist-info/METADATA
LibreriaViajes_UxueAinara-0.5.6.dist-info/WHEEL
LibreriaViajes_UxueAinara-0.5.6.dist-info/top_level.txt
LibreriaViajes_UxueAinara-0.5.6.dist-info/RECORD
