Metadata-Version: 2.1
Name: LibreriaViajes-UxueAinara
Version: 0.5.6
Summary: Una librería para obtener información de interés sobre su destino.
Home-page: UNKNOWN
Author: Ainara Hoyos y Uxue Garcia
License: UNKNOWN
Platform: UNKNOWN
Requires-Dist: requests (>=2.0.0)
Requires-Dist: termcolor (>=1.1.0)
